example_devup/__init__.py
example_devup/hello.py
example_devup-0.0.1.dist-info/LICENSE
example_devup-0.0.1.dist-info/METADATA
example_devup-0.0.1.dist-info/WHEEL
example_devup-0.0.1.dist-info/top_level.txt
example_devup-0.0.1.dist-info/RECORD
