Metadata-Version: 2.1
Name: example-devup
Version: 0.0.1
Summary: Ví dụ về cách upload package
Author-email: DEVUP <author@example.com>
Classifier: Programming Language :: Python :: 3
Classifier: License :: OSI Approved :: MIT License
Classifier: Operating System :: OS Independent
Requires-Python: >=3.7
License-File: LICENSE
